{
  "timestamp": "2026-03-09T18:28:31.976Z",
  "passed": 10,
  "total": 10,
  "results": [
    {
      "check": "Integration provider collectors implemented",
      "pass": true,
      "detail": "AWS, GitHub, Okta, Google Workspace, and Azure collectors exist"
    },
    {
      "check": "Control monitoring engine implemented",
      "pass": true,
      "detail": "Scheduler -> collectors -> evaluation -> evidence -> risk flow is implemented"
    },
    {
      "check": "Evidence auto collection implemented",
      "pass": true,
      "detail": "Automated evidence collection, validation, and storage are implemented"
    },
    {
      "check": "Compliance scanner modules implemented",
      "pass": true,
      "detail": "Port, TLS, DNS/email scanners and report aggregation are implemented"
    },
    {
      "check": "Risk automation engine implemented",
      "pass": true,
      "detail": "Failed controls auto-create risks and remediation tasks"
    },
    {
      "check": "Dashboard APIs available",
      "pass": true,
      "detail": "Operational dashboard APIs are implemented"
    },
    {
      "check": "Prisma schema supports integration accounts and evidence JSON",
      "pass": true,
      "detail": "Schema supports integration account metadata and evidence payloads"
    },
    {
      "check": "Phase 4 scripts registered",
      "pass": true,
      "detail": "package.json exposes phase4 governance scripts"
    },
    {
      "check": "Phase 4 workflow exists",
      "pass": true,
      "detail": "Phase 4 release gate workflow is configured"
    },
    {
      "check": "Phase matrix includes Phase 4 automation scope",
      "pass": true,
      "detail": "Phase matrix tracks Phase 4 objective"
    }
  ]
}
